{
  "model": {
    "type": "minecraft:composite",
    "models": [
      {
        "type": "minecraft:select",
        "cases": [
          {
            "model": {
              "type": "minecraft:model",
              "model": "odyssey:item/weapons/katana/composite/blade_iridium"
            },
            "when": "blade"
          },
          {
            "model": {
              "type": "minecraft:model",
              "model": "odyssey:item/weapons/katana/composite/seraph_blade_iridium"
            },
            "when": "seraph_blade"
          },
          {
            "model": {
              "type": "minecraft:model",
              "model": "odyssey:item/weapons/katana/composite/imperial_blade_iridium"
            },
            "when": "imperial_blade"
          },
          {
            "model": {
              "type": "minecraft:model",
              "model": "odyssey:item/weapons/katana/composite/fancy_blade_iridium"
            },
            "when": "fancy_blade"
          },
          {
            "model": {
              "type": "minecraft:model",
              "model": "odyssey:item/weapons/katana/composite/voyager_blade_iridium"
            },
            "when": "voyager_blade"
          }
        ],
        "fallback": {
          "type": "minecraft:model",
          "model": "odyssey:item/weapons/katana/composite/blade_iridium"
        },
        "property": "minecraft:custom_model_data",
        "index": 1
      },
      {
        "type": "minecraft:select",
        "cases": [
          {
            "model": {
              "type": "minecraft:model",
              "model": "odyssey:item/weapons/katana/composite/handle_iridium"
            },
            "when": "handle"
          }
        ],
        "fallback": {
          "type": "minecraft:model",
          "model": "odyssey:item/weapons/katana/composite/handle_iridium"
        },
        "property": "minecraft:custom_model_data",
        "index": 2
      },
      {
        "type": "minecraft:select",
        "cases": [
          {
            "model": {
              "type": "minecraft:model",
              "model": "odyssey:item/weapons/katana/composite/hilt_iridium"
            },
            "when": "hilt"
          },
          {
            "model": {
              "type": "minecraft:model",
              "model": "odyssey:item/weapons/katana/composite/seraph_hilt_iridium"
            },
            "when": "seraph_hilt"
          },
          {
            "model": {
              "type": "minecraft:model",
              "model": "odyssey:item/weapons/katana/composite/imperial_hilt_iridium"
            },
            "when": "imperial_hilt"
          },
          {
            "model": {
              "type": "minecraft:model",
              "model": "odyssey:item/weapons/katana/composite/fancy_hilt_iridium"
            },
            "when": "fancy_hilt"
          },
          {
            "model": {
              "type": "minecraft:model",
              "model": "odyssey:item/weapons/katana/composite/voyager_hilt_iridium"
            },
            "when": "voyager_hilt"
          }
        ],
        "fallback": {
          "type": "minecraft:model",
          "model": "odyssey:item/weapons/katana/composite/hilt_iridium"
        },
        "property": "minecraft:custom_model_data",
        "index": 3
      },
      {
        "type": "minecraft:select",
        "cases": [
          {
            "model": {
              "type": "minecraft:model",
              "model": "odyssey:item/weapons/katana/composite/pommel_iridium"
            },
            "when": "pommel"
          },
          {
            "model": {
              "type": "minecraft:model",
              "model": "odyssey:item/weapons/katana/composite/seraph_pommel_iridium"
            },
            "when": "seraph_pommel"
          },
          {
            "model": {
              "type": "minecraft:model",
              "model": "odyssey:item/weapons/katana/composite/imperial_pommel_iridium"
            },
            "when": "imperial_pommel"
          },
          {
            "model": {
              "type": "minecraft:model",
              "model": "odyssey:item/weapons/katana/composite/fancy_pommel_iridium"
            },
            "when": "fancy_pommel"
          },
          {
            "model": {
              "type": "minecraft:model",
              "model": "odyssey:item/weapons/katana/composite/voyager_pommel_iridium"
            },
            "when": "voyager_pommel"
          }
        ],
        "fallback": {
          "type": "minecraft:model",
          "model": "odyssey:item/weapons/katana/composite/pommel_iridium"
        },
        "property": "minecraft:custom_model_data",
        "index": 4
      }
    ]
  }
}