{
  "parent": "minecraft:item/handheld",
  "textures": {
    "layer0": "minecraft:item/golden_hoe"
  },
  "overrides": [
    {
      "model": "odyssey:item/weapon/golden_scythe",
      "predicate": {
        "custom_model_data": 6905292
      }
    },
    {
      "model": "odyssey:item/tool/copper_hoe",
      "predicate": {
        "custom_model_data": 6905509
      }
    },
    {
      "model": "odyssey:item/weapon/copper_scythe",
      "predicate": {
        "custom_model_data": 6905592
      }
    }
  ]
}